setup.py
bin/jagss
jagss/__init__.py
jagss/createSite.py
jagss/sftpsync.py
jagss.egg-info/PKG-INFO
jagss.egg-info/SOURCES.txt
jagss.egg-info/dependency_links.txt
jagss.egg-info/not-zip-safe
jagss.egg-info/requires.txt
jagss.egg-info/top_level.txt