Metadata-Version: 1.0
Name: jagss
Version: 0.0.3
Summary: Just another generator for static sites
Home-page: https://jagss.rpy.xyz
Author: Evan Sonderegger
Author-email: evan@rpy.xyz
License: MIT
Platform: UNKNOWN
